pylsp_rope/__init__.py
pylsp_rope/commands.py
pylsp_rope/lsp_diff.py
pylsp_rope/plugin.py
pylsp_rope/project.py
pylsp_rope/refactoring.py
pylsp_rope/rope.py
pylsp_rope/text.py
pylsp_rope/typing.py
pylsp_rope-0.1.17.dist-info/AUTHORS.txt
pylsp_rope-0.1.17.dist-info/LICENSE
pylsp_rope-0.1.17.dist-info/METADATA
pylsp_rope-0.1.17.dist-info/WHEEL
pylsp_rope-0.1.17.dist-info/entry_points.txt
pylsp_rope-0.1.17.dist-info/top_level.txt
pylsp_rope-0.1.17.dist-info/RECORD
