Metadata-Version: 2.1
Name: pylsp-rope
Version: 0.1.17
Summary: Extended refactoring capabilities for Python LSP Server using Rope.
Home-page: https://github.com/python-rope/pylsp-rope
Author: Lie Ryan
Author-email: lie.1296@gmail.com
License: MIT license
Classifier: Programming Language :: Python
Classifier: Operating System :: OS Independent
Classifier: Development Status :: 2 - Pre-Alpha
Classifier: Intended Audience :: Developers
Classifier: Topic :: Text Editors :: Integrated Development Environments (IDE)
Classifier: Topic :: Software Development
Classifier: License :: OSI Approved :: MIT License
Requires-Python: >=3.6
License-File: LICENSE
License-File: AUTHORS.txt
Requires-Dist: python-lsp-server
Requires-Dist: rope >=0.21.0
Requires-Dist: typing-extensions ; python_version < "3.10"
Provides-Extra: dev
Requires-Dist: build ; extra == 'dev'
Requires-Dist: pytest ; extra == 'dev'
Requires-Dist: twine ; extra == 'dev'
Provides-Extra: test
Requires-Dist: flake8 ; extra == 'test'
Requires-Dist: pytest ; extra == 'test'
Requires-Dist: pytest-cov ; extra == 'test'
